django_saml2_auth_lw/__init__.py
django_saml2_auth_lw/urls.py
django_saml2_auth_lw/views.py
django_saml2_auth_lw/templates/django_saml2_auth/denied.html
django_saml2_auth_lw/templates/django_saml2_auth/signout.html
django_saml2_auth_lw-2.3.0.dist-info/AUTHORS.rst
django_saml2_auth_lw-2.3.0.dist-info/LICENSE
django_saml2_auth_lw-2.3.0.dist-info/METADATA
django_saml2_auth_lw-2.3.0.dist-info/WHEEL
django_saml2_auth_lw-2.3.0.dist-info/top_level.txt
django_saml2_auth_lw-2.3.0.dist-info/RECORD
