Metadata-Version: 2.1
Name: django-saml2-auth-lw
Version: 2.3.0
Summary: Django SAML2 Authentication Made Easy. Easily integrate with SAML2 SSO identity providers like Okta
Home-page: https://github.com/Lotterywest/django-saml2-auth-lw
Author: Fang Li, Lotterywest GoRillas Team
Author-email: surivlee+djsaml2auth@gmail.com, Gorillas@lotterywest.wa.gov.au
License: Apache 2.0
Keywords: Django SAML2 Authentication Made Easy,integrate with SAML2 SSO such as Okta easily
Platform: UNKNOWN
Classifier: Development Status :: 5 - Production/Stable
Classifier: Intended Audience :: Developers
Classifier: Topic :: Software Development :: Libraries :: Python Modules
Classifier: License :: OSI Approved :: Apache Software License
Classifier: Framework :: Django :: 1.5
Classifier: Framework :: Django :: 1.6
Classifier: Framework :: Django :: 1.7
Classifier: Framework :: Django :: 1.8
Classifier: Framework :: Django :: 1.9
Classifier: Framework :: Django :: 1.10
Classifier: Framework :: Django :: 1.10
Classifier: Framework :: Django :: 3.2
Classifier: Framework :: Django :: 4.0
Classifier: Programming Language :: Python :: 2
Classifier: Programming Language :: Python :: 2.6
Classifier: Programming Language :: Python :: 2.7
Classifier: Programming Language :: Python :: 3
Classifier: Programming Language :: Python :: 3.3
Classifier: Programming Language :: Python :: 3.4
Classifier: Programming Language :: Python :: 3.5
Classifier: Programming Language :: Python :: 3.6
Classifier: Programming Language :: Python :: 3.7
Classifier: Programming Language :: Python :: 3.8
Classifier: Programming Language :: Python :: 3.9
Classifier: Programming Language :: Python :: 3.10
License-File: LICENSE
License-File: AUTHORS.rst
Requires-Dist: pysaml2 (>=4.5.0)
Requires-Dist: drf-jwt
